alembic_migration_fixtures/__init__.py
alembic_migration_fixtures/fixtures.py
alembic_migration_fixtures-0.2.0.dist-info/LICENSE
alembic_migration_fixtures-0.2.0.dist-info/METADATA
alembic_migration_fixtures-0.2.0.dist-info/WHEEL
alembic_migration_fixtures-0.2.0.dist-info/entry_points.txt
alembic_migration_fixtures-0.2.0.dist-info/RECORD
