Metadata-Version: 2.1
Name: alembic-migration-fixtures
Version: 0.2.0
Summary: Pytest fixtures for tests involving databases managed by alembic migrations
Home-page: https://github.com/Barbora-Data-Science/alembic-migration-fixtures
License: Apache-2.0
Author: Saulius Beinorius
Author-email: saulius.beinorius@gmail.com
Maintainer: Saulius Beinorius
Maintainer-email: saulius.beinorius@gmail.com
Requires-Python: >=3.7,<4.0
Classifier: License :: OSI Approved :: Apache Software License
Classifier: Programming Language :: Python :: 3
Classifier: Programming Language :: Python :: 3.7
Classifier: Programming Language :: Python :: 3.8
Classifier: Programming Language :: Python :: 3.9
Classifier: Programming Language :: Python :: 3.10
Classifier: Programming Language :: Python :: 3.11
Classifier: Topic :: Software Development :: Libraries :: Python Modules
Requires-Dist: SQLAlchemy (>=1.3.19,<1.5)
Requires-Dist: alembic (>=1.4.2,<2)
Requires-Dist: pytest (>=5.2,<7.0)
Project-URL: Repository, https://github.com/Barbora-Data-Science/alembic-migration-fixtures
